network_automation/__init__.py
network_automation/apic.py
network_automation/cisco.py
network_automation/environment.py
network_automation/netbox.py
network_automation/nfvis.py
network_automation/utils.py
network_automation/vmanage.py
network_automation-0.1.15.dist-info/LICENSE
network_automation-0.1.15.dist-info/METADATA
network_automation-0.1.15.dist-info/WHEEL
network_automation-0.1.15.dist-info/RECORD
